{
  "level_names": {
    "e0:title_screen": { "preposition": "на", "nomn": "Главный экран", "loct": "Главном экране" },
    "e0:bridge_corridor": { "preposition": "в", "nomn": "Стыковочный коридор", "loct": "Стыковочном коридоре" },
    "e0:lobby": { "preposition": "в", "nomn": "Вестибюль", "loct": "Вестибюле" },
    "e0:machine_hall": { "preposition": "в", "nomn": "Машинный зал", "loct": "Машинном зале" },
    "e0:space_greenhouse": { "preposition": "в", "nomn": "Космическая оранжерея", "loct": "Космической оранжерее" },
    "e0:outer_skeleton": { "preposition": "на", "nomn": "Внешний скелет", "loct": "Внешнем скелете" },
    "e0:illusion_room": { "preposition": "в", "nomn": "Комната Иллюзии", "loct": "Комнате Иллюзии" },
    "default": { "preposition": "в", "nomn": "неизвестный отсек", "loct": "неизвестном отсеке" }
  },
  "command_responses": {
    "command_unknown": [
      "Я Вас слышу, но не понимаю команду.",
      "Команда не распознана. Повторите ввод."
    ],
    "hint_nearest": {
      "found": [
        "Вызываю подсказку.",
        "Подсказка запущена."
      ],
      "not_found": [
        "Подсказки для заданий недоступны.",
        "Здесь нет заданий для вызова подсказки."
      ]
    },
    "hint_truthtable": {
      "template": [
        "Вывожу таблицу к {operator_datv}.",
        "Таблица истинности {operator_gent}."
      ],
      "operator": {
        "Identity": {
          "nomn": "тождество", "gent": "тождества", "datv": "тождеству"
        },
        "Not": {
          "nomn": "инверсия", "gent": "инверсии", "datv": "инверсии"
        },
        "And": {
          "nomn": "конъюнкция", "gent": "конъюнкции", "datv": "конъюнкции"
        },
        "Or": {
          "nomn": "дизъюнкция", "gent": "дизъюнкции", "datv": "дизъюнкции"
        },
        "Xor": {
          "nomn": "исключающее ИЛИ", "gent": "исключающего ИЛИ", "datv": "исключающему ИЛИ"
        },
        "ImplKleene": {
          "nomn": "импликация Клини", "gent": "импликации Клини", "datv": "импликации Клини"
        },
        "ImplLukasiewicz": {
          "nomn": "импликация Лукасевича", "gent": "импликации Лукасевича", "datv": "импликации Лукасевича"
        },
        "NonaryPlus": {
          "nomn": "сложение", "gent": "сложения", "datv": "сложению"
        },
        "NonaryMinus": {
          "nomn": "вычитание", "gent": "вычитания", "datv": "вычитанию"
        },
        "NonaryConcat": {
          "nomn": "конкатенация", "gent": "конкатенации", "datv": "конкатенации"
        }
      }
    },
    "settings_volume": {
      "template": "{group} {action}.",
      "groups": {
        "master": "Общая громкость звука",
        "music": "Громкость музыки",
        "sfx": "Громкость спецэффектов",
        "voice": "Громкость голоса"
      },
      "actions": {
        "increase": "увеличена",
        "decrease": "уменьшена",
        "mute": "заглушена"
      }
    },
    "progress_level": {
      "templates": {
        "no_tasks_found": "Вы на уровне: {level_name_nomn}.",
        "some_tasks_done": "Вы {level_name_preposition} {level_name_loct}. Осталось выполнить {remaining_tasks_count_nomn} {task_accs} из {total_tasks_count_gent}",
        "all_tasks_done": "Вы {level_name_preposition} {level_name_loct}. Выполнены все задачи."
      },
      "task": {
        "accs": { "singular": "задачу", "dual": "задачи", "plural": "задач" }
      }
    },
    "fact_random": {
      "logic": [
        {
          "display_text": "Первый троичный компьютер, «Сетунь», построили в СССР в 1950-х.",
          "tts_text": "Первый троичный компьютер Сетунь, построили в Советском Союзе в пятидесятых."
        },
        {
          "display_text": "Троичный разряд (трит) хранит чуть больше чем 1.5 бита информации.",
          "tts_text": "Троичный разряд, трит, хранит чуть больше чем полтора бита информации."
        },
        {
          "display_text": "Импликация Клини и Лукасевича работает почти одинаково, но одна пара аргументов отличается.",
          "tts_text": "Импликация Клини и Лукасевича работает почти одинаково, но одна пара аргументов отличается."
        },
        {
          "display_text": "Троичную логику используют в базах данных и в логике открытого мира.",
          "tts_text": "Троичную логику используют в базах данных и в логике открытого мира."
        },
        {
          "display_text": "9-чную систему использовали в компьютере «Сетунь», т. к. 9 — это 3 в квадрате.",
          "tts_text": "Девятеричную систему использовали в компьютере «Сетунь», т. к. девять — это три в квадрате."
        }
      ],
      "lore": {
        "any_level": [
          {
            "display_text": "«Пульсар» — коммуникационная станция для передачи сигналов по Солнечной системе.",
            "tts_text": "Пульсар, коммуникационная станция для передачи сигналов по Солнечной системе."
          },
          {
            "display_text": "На станции «Пульсар» произошёл сбой связи, Вас отправили его расследовать.",
            "tts_text": "На станции Пульсар произошёл сбой связи, Вас отправили его расследовать."
          },
          {
            "display_text": "Получите 3 артефакта, чтобы завершить кампанию.",
            "tts_text": "Получите три артефакта, чтобы завершить кампанию."
          },
          {
            "display_text": "Остерегайтесь ИИ «Гиперион», его шпионы повсюду.",
            "tts_text": "Остерегайтесь Гипериона, его шпионы повсюду."
          },
          {
            "display_text": "Желаю вам счастья, крепкого здоровья, больших успехов в научной работе СИСТЕМАТИЧЕСКИ.",
            "tts_text": "Желаю вам счастья, крепкого здоровья, больших успехов в научной работе *систематически*."
          }
        ],
        "e0:bridge_corridor": [],
        "e0:lobby": [
          {
            "display_text": "Из этого зала можно добраться в любой сектор станции.",
            "tts_text": "Из этого зала можно добраться в любой сектор станции."
          }
        ],
        "e0:machine_hall": [
          {
            "display_text": "В машинном зале возгорание, будьте осторожны.",
            "tts_text": "В машинном зале возгорание, будьте осторожны."
          },
          {
            "display_text": "Исправьте схемы, чтобы потушить огонь.",
            "tts_text": "Исправьте схемы, чтобы потушить огонь."
          }
        ],
        "e0:space_greenhouse": [
          {
            "display_text": "Космическая оранжерея симулирует естественный цикл дня и ночи.",
            "tts_text": "Космическая оранжерея симулирует естественный цикл дня и ночи."
          },
          {
            "display_text": "Вращение станции позволяет растениям расти, как на Земле, и даже лучше.",
            "tts_text": "Вращение станции позволяет растениям расти как на Земле, и даже лучше."
          }
        ],
        "e0:outer_skeleton": [
          {
            "display_text": "В невесомости вы летите в направлении взгляда.",
            "tts_text": "В невесомости вы летите в направлении взгляда."
          },
          {
            "display_text": "Смотрите, роботы ведут починку коммуникационной антенны.",
            "tts_text": "Смотрите, роботы ведут починку коммуникационной антенны."
          }
        ],
        "e0:illusion_room": [
          {
            "display_text": "Пожалуйста, будьте дружелюбны к Иллюзии.",
            "tts_text": "Пожалуйста будьте дружелюбны к Иллюзии."
          },
          {
            "display_text": "Иллюзия — голограмма, созданная Гиперионом, но она дружелюбна.",
            "tts_text": "Иллюзия это голограмма, созданная Гиперионом, но она дружелюбна."
          },
          {
            "display_text": "Красивая комната, не правда ли?",
            "tts_text": "Красивая комната, не правда ли?"
          },
          {
            "display_text": "Посмотрите, как сияет здесь Луна!",
            "tts_text": "Посмотрите как сияет здесь Луна."
          }
        ]
      }
    }
  }
}